setup.py
Sports_Recommender/MergeTags.py
Sports_Recommender/RedditConsolidated.py
Sports_Recommender/Scrapers.py
Sports_Recommender/TwitterConsolidated.py
Sports_Recommender/__init__.py
Sports_Recommender/combine.py
Sports_Recommender/reccomendation_pt2.py
Sports_Recommender/tagtrialpt2.py
Sports_Recommender.egg-info/PKG-INFO
Sports_Recommender.egg-info/SOURCES.txt
Sports_Recommender.egg-info/dependency_links.txt
Sports_Recommender.egg-info/requires.txt
Sports_Recommender.egg-info/top_level.txt