Metadata-Version: 2.1
Name: Sports-Recommender
Version: 0.0.1
Summary: Recommendations of sports content
Author: Mathew Mammen Jacob
Author-email: <mathew.mammenjacob@gmail.com>
License: UNKNOWN
Keywords: python,package,Recommender
Platform: UNKNOWN
Classifier: Development Status :: 3 - Alpha
Classifier: Intended Audience :: Education
Classifier: Programming Language :: Python :: 2
Classifier: Programming Language :: Python :: 3
Classifier: Operating System :: MacOS :: MacOS X
Classifier: Operating System :: Microsoft :: Windows
